README.txt
setup.cfg
setup.py
collective/__init__.py
collective.sylvester.egg-info/PKG-INFO
collective.sylvester.egg-info/SOURCES.txt
collective.sylvester.egg-info/dependency_links.txt
collective.sylvester.egg-info/entry_points.txt
collective.sylvester.egg-info/namespace_packages.txt
collective.sylvester.egg-info/not-zip-safe
collective.sylvester.egg-info/requires.txt
collective.sylvester.egg-info/top_level.txt
collective/sylvester/TODO.txt
collective/sylvester/__init__.py
collective/sylvester/configure.zcml
collective/sylvester/profiles.zcml
collective/sylvester/remember.zcml
collective/sylvester/utils.py
collective/sylvester/browser/__init__.py
collective/sylvester/browser/adapters.py
collective/sylvester/browser/configure.zcml
collective/sylvester/browser/interfaces.py
collective/sylvester/browser/kssviews.py
collective/sylvester/browser/plugins.js
collective/sylvester/browser/plugins.zcml
collective/sylvester/browser/utilities.py
collective/sylvester/browser/viewlets.py
collective/sylvester/browser/views.py
collective/sylvester/browser/plugins/__init__.py
collective/sylvester/browser/plugins/directmessages/__init__.py
collective/sylvester/browser/plugins/directmessages/configure.zcml
collective/sylvester/browser/plugins/directmessages/directmessages.css
collective/sylvester/browser/plugins/directmessages/directmessages.kss
collective/sylvester/browser/plugins/directmessages/directmessages.png
collective/sylvester/browser/plugins/directmessages/directmessages.pt
collective/sylvester/browser/plugins/directmessages/viewlets.py
collective/sylvester/browser/plugins/following/__init__.py
collective/sylvester/browser/plugins/following/configure.zcml
collective/sylvester/browser/plugins/following/following.css
collective/sylvester/browser/plugins/following/following.kss
collective/sylvester/browser/plugins/following/following.png
collective/sylvester/browser/plugins/following/following.pt
collective/sylvester/browser/plugins/following/kssviews.py
collective/sylvester/browser/plugins/following/viewlets.py
collective/sylvester/browser/plugins/replies/__init__.py
collective/sylvester/browser/plugins/replies/configure.zcml
collective/sylvester/browser/plugins/replies/replies.css
collective/sylvester/browser/plugins/replies/replies.kss
collective/sylvester/browser/plugins/replies/replies.png
