Metadata-Version: 1.0
Name: collective.sylvester
Version: 0.2
Summary: A twitter client for Plone. Tweetie is toast.
Home-page: UNKNOWN
Author: Hedley Roos
Author-email: hedley@upfrontsystems.co.za
License: GPL
Platform: UNKNOWN
Classifier: Framework :: Plone
Classifier: Framework :: Zope2
Classifier: Programming Language :: Python
Classifier: Topic :: Software Development :: Libraries :: Python Modules
